stdpipeIO/__init__.py
stdpipeIO/std_pipe_io.py
stdpipeIO-0.1.4.dist-info/METADATA
stdpipeIO-0.1.4.dist-info/WHEEL
stdpipeIO-0.1.4.dist-info/top_level.txt
stdpipeIO-0.1.4.dist-info/RECORD
