Metadata-Version: 2.2
Name: stdpipeIO
Version: 0.1.4
Summary: A simple decorator for receiving and sending data via the standard pipe
Author: Greendog
Author-email: x6reend0g@foxmail.com
Classifier: Programming Language :: Python :: 3
Classifier: License :: OSI Approved :: MIT License
Classifier: Operating System :: OS Independent
Requires-Python: >=3.6
Dynamic: author
Dynamic: author-email
Dynamic: classifier
Dynamic: description
Dynamic: description-content-type
Dynamic: requires-python
Dynamic: summary
